kDBCV/DBCV.py
kDBCV/__init__.py
kDBCV-1.0.0.dist-info/LICENSE
kDBCV-1.0.0.dist-info/METADATA
kDBCV-1.0.0.dist-info/WHEEL
kDBCV-1.0.0.dist-info/top_level.txt
kDBCV-1.0.0.dist-info/RECORD
