Metadata-Version: 2.1
Name: kDBCV
Version: 1.0.0
Summary: Efficient implementation of DBCV with a k-dimensional tree
Home-page: https://github.com/Kaufman-Lab-Columbia/k-DBCV
Author: Joseph L. Hammer, Alexander J. Devanny
Author-email: jhammer3018@gmail.com
License: MIT
Keywords: cluster clusters clustering
Classifier: License :: OSI Approved :: MIT License
Classifier: Programming Language :: Python :: 3
Classifier: Topic :: Scientific/Engineering
License-File: LICENSE
Requires-Dist: numpy<2,>=1.20.0
Requires-Dist: scipy<=1.14.1,>=1.7.0
